{
  "dataset_revision": "e7a26af6f3ae46b30dde8737f02c07b1505bcc73",
  "task_name": "MedrxivClusteringP2P.v2",
  "mteb_version": "1.38.38",
  "scores": {
    "test": [
      {
        "v_measures": {
          "Level 0": [
            0.342251,
            0.338502,
            0.343871,
            0.329552,
            0.348207,
            0.329692,
            0.331961,
            0.322746,
            0.34273,
            0.332164
          ]
        },
        "v_measure": 0.336167,
        "v_measure_std": 0.007677,
        "main_score": 0.336167,
        "hf_subset": "default",
        "languages": [
          "eng-Latn"
        ]
      }
    ]
  },
  "evaluation_time": 59.236602783203125,
  "kg_co2_emissions": null
}
